a2y_builda2y/__init__.py
a2y_builda2y-1.2.0.dist-info/LICENSE
a2y_builda2y-1.2.0.dist-info/METADATA
a2y_builda2y-1.2.0.dist-info/WHEEL
a2y_builda2y-1.2.0.dist-info/top_level.txt
a2y_builda2y-1.2.0.dist-info/RECORD
