Metadata-Version: 2.1
Name: a2y-builda2y
Version: 1.2.0
Summary: UNKNOWN
Home-page: http://www.kersci.com/a2y/builda2y.html
Author: Yu Han
Author-email: hanjunyu@163.com
License: Private
Platform: Windows
Platform: Linux
Classifier: Development Status :: 4 - Beta
Classifier: Intended Audience :: Developers
Classifier: License :: Free For Educational Use
Classifier: Programming Language :: Python :: 3.6
Classifier: Operating System :: Microsoft :: Windows :: Windows 10
Classifier: Operating System :: POSIX :: Linux
Requires-Dist: setuptools >=40.0.0
Requires-Dist: wheel >=0.34.0
Requires-Dist: cython >=3.0
